ajsonapi/__init__.py
ajsonapi/application.py
ajsonapi/attribute.py
ajsonapi/conftest.py
ajsonapi/conversions.py
ajsonapi/document.py
ajsonapi/environments.py
ajsonapi/errors.py
ajsonapi/events.py
ajsonapi/exceptions.py
ajsonapi/field.py
ajsonapi/headers.py
ajsonapi/id.py
ajsonapi/id_value.py
ajsonapi/init.py
ajsonapi/json_api.py
ajsonapi/logging.py
ajsonapi/postgres.py
ajsonapi/query.py
ajsonapi/relationships.py
ajsonapi/requests.py
ajsonapi/responses.py
ajsonapi/table.py
ajsonapi/toposort.py
ajsonapi/types.py
ajsonapi/uri/__init__.py
ajsonapi/uri/collection.py
ajsonapi/uri/object.py
ajsonapi/uri/related.py
ajsonapi/uri/relationship.py
ajsonapi/uri/resource.py
ajsonapi-0.9.4.dist-info/LICENSE
ajsonapi-0.9.4.dist-info/METADATA
ajsonapi-0.9.4.dist-info/WHEEL
ajsonapi-0.9.4.dist-info/top_level.txt
ajsonapi-0.9.4.dist-info/RECORD
