Metadata-Version: 2.1
Name: ajsonapi
Version: 0.9.4
Summary: Asynchronous JSON API
Home-page: https://gitlab.com/rvdg/ajsonapi
Author: Roel van der Goot
Author-email: roel@simplecuriosities.com
Classifier: Programming Language :: Python :: 3.7
Classifier: License :: OSI Approved :: MIT License
Classifier: Operating System :: OS Independent
License-File: LICENSE
Requires-Dist: asyncio
Requires-Dist: aiohttp
Requires-Dist: asyncpg
